README.rst
setup.py
new_html/__init__.py
new_html/__main__.py
new_html/new_html.py
new_html/stuff.py
new_html.egg-info/PKG-INFO
new_html.egg-info/SOURCES.txt
new_html.egg-info/dependency_links.txt
new_html.egg-info/entry_points.txt
new_html.egg-info/top_level.txt