Metadata-Version: 1.0
Name: new-html
Version: 0.3.0
Summary: Python command line html creator
Home-page: https://github.com/oscarvazquez/command_line_tool_demo
Author: Oscar Vazquez
Author-email: oscar.vazquez2012@gmail.com
License: UNKNOWN
Platform: UNKNOWN
